azure/mgmt/mixedreality/__init__.py
azure/mgmt/mixedreality/_configuration.py
azure/mgmt/mixedreality/_mixed_reality_client.py
azure/mgmt/mixedreality/_version.py
azure/mgmt/mixedreality/aio/__init__.py
azure/mgmt/mixedreality/aio/_configuration.py
azure/mgmt/mixedreality/aio/_mixed_reality_client.py
azure/mgmt/mixedreality/aio/operations/__init__.py
azure/mgmt/mixedreality/aio/operations/_mixed_reality_client_operations.py
azure/mgmt/mixedreality/aio/operations/_object_anchors_accounts_operations.py
azure/mgmt/mixedreality/aio/operations/_operations.py
azure/mgmt/mixedreality/aio/operations/_remote_rendering_accounts_operations.py
azure/mgmt/mixedreality/aio/operations/_spatial_anchors_accounts_operations.py
azure/mgmt/mixedreality/models/__init__.py
azure/mgmt/mixedreality/models/_mixed_reality_client_enums.py
azure/mgmt/mixedreality/models/_models.py
azure/mgmt/mixedreality/models/_models_py3.py
azure/mgmt/mixedreality/operations/__init__.py
azure/mgmt/mixedreality/operations/_mixed_reality_client_operations.py
azure/mgmt/mixedreality/operations/_object_anchors_accounts_operations.py
azure/mgmt/mixedreality/operations/_operations.py
azure/mgmt/mixedreality/operations/_remote_rendering_accounts_operations.py
azure/mgmt/mixedreality/operations/_spatial_anchors_accounts_operations.py
azure_mgmt_mixedreality-1.0.0.dist-info/METADATA
azure_mgmt_mixedreality-1.0.0.dist-info/WHEEL
azure_mgmt_mixedreality-1.0.0.dist-info/top_level.txt
azure_mgmt_mixedreality-1.0.0.dist-info/RECORD
