Metadata-Version: 2.1
Name: azure-mgmt-mixedreality
Version: 1.0.0
Summary: Microsoft Azure Mixed Reality Management Client Library for Python
Home-page: https://github.com/Azure/azure-sdk-for-python
Author: Microsoft Corporation
Author-email: azpysdkhelp@microsoft.com
License: MIT License
Platform: UNKNOWN
Classifier: Development Status :: 4 - Beta
Classifier: Programming Language :: Python
Classifier: Programming Language :: Python :: 2
Classifier: Programming Language :: Python :: 2.7
Classifier: Programming Language :: Python :: 3
Classifier: Programming Language :: Python :: 3.4
Classifier: Programming Language :: Python :: 3.5
Classifier: Programming Language :: Python :: 3.6
Classifier: Programming Language :: Python :: 3.7
Classifier: License :: OSI Approved :: MIT License
Requires-Dist: msrest (>=0.6.21)
Requires-Dist: azure-common (~=1.1)
Requires-Dist: azure-mgmt-core (<2.0.0,>=1.2.0)
Requires-Dist: azure-mgmt-nspkg ; python_version<'3.0'
